torch_ort/__init__.py
torch_ort/_version.py
torch_ort/configure/__main__.py
torch_ort/experimental/__init__.py
torch_ort/experimental/graph_config.py
torch_ort/experimental/json_config/__init__.py
torch_ort/optim/__init__.py
torch_ort/utils/data/__init__.py
torch_ort-1.19.2.dist-info/METADATA
torch_ort-1.19.2.dist-info/WHEEL
torch_ort-1.19.2.dist-info/top_level.txt
torch_ort-1.19.2.dist-info/RECORD
