Metadata-Version: 2.1
Name: torch-ort
Version: 1.19.2
Summary: Accelerate PyTorch models with ONNX Runtime
Home-page: https://github.com/pytorch/ort
Author: torch-ort contributors
License: UNKNOWN
Project-URL: Bug Tracker, https://github.com/pytorch/ort/issues
Platform: UNKNOWN
Classifier: Programming Language :: Python :: 3
Classifier: License :: OSI Approved :: MIT License
Classifier: Operating System :: OS Independent
Requires-Python: >=3.8
Requires-Dist: onnxruntime-training (>=1.7.0)
Requires-Dist: torch (>=1.8)
